reformat_money/__init__.py
reformat_money/__main__.py
reformat_money/arguments.py
reformat_money/file_formatter.py
reformat_money/file_searcher.py
reformat_money/match.py
reformat_money/run.py
reformat_money/settings.py
reformat_money/text_formatter.py
reformat_money-0.0.2.dist-info/LICENSE
reformat_money-0.0.2.dist-info/METADATA
reformat_money-0.0.2.dist-info/WHEEL
reformat_money-0.0.2.dist-info/entry_points.txt
reformat_money-0.0.2.dist-info/top_level.txt
reformat_money-0.0.2.dist-info/RECORD
